{
	"configurations" : 
	[
		{
			"directories" : 
			[
				{
					"build" : ".",
					"hasInstallRule" : true,
					"jsonFile" : "directory-.-Release-d5fb78b22f907934f526.json",
					"minimumCMakeVersion" : 
					{
						"string" : "3.12"
					},
					"projectIndex" : 0,
					"source" : ".",
					"targetIndexes" : 
					[
						0,
						1
					]
				}
			],
			"name" : "Release",
			"projects" : 
			[
				{
					"directoryIndexes" : 
					[
						0
					],
					"name" : "dummy2-gripperv3_moveit_config",
					"targetIndexes" : 
					[
						0,
						1
					]
				}
			],
			"targets" : 
			[
				{
					"directoryIndex" : 0,
					"id" : "dummy2-gripperv3_moveit_config_uninstall::@6890427a1f51a3e7e1df",
					"jsonFile" : "target-dummy2-gripperv3_moveit_config_uninstall-Release-caa0514821abea67a4d7.json",
					"name" : "dummy2-gripperv3_moveit_config_uninstall",
					"projectIndex" : 0
				},
				{
					"directoryIndex" : 0,
					"id" : "uninstall::@6890427a1f51a3e7e1df",
					"jsonFile" : "target-uninstall-Release-b6c6e3d26d90d7ef0fd2.json",
					"name" : "uninstall",
					"projectIndex" : 0
				}
			]
		}
	],
	"kind" : "codemodel",
	"paths" : 
	{
		"build" : "/home/futill/dummy2_hand_eye_calibration_ws/build/dummy2-gripperv3_moveit_config",
		"source" : "/home/futill/dummy2_hand_eye_calibration_ws/src/dummy2-gripperv3_moveit_config"
	},
	"version" : 
	{
		"major" : 2,
		"minor" : 3
	}
}
